setup.py
django_pjaxr/__init__.py
django_pjaxr/context_processors.py
django_pjaxr/mixins.py
django_pjaxr/models.py
django_pjaxr/test_settings.py
django_pjaxr/test_views.py
django_pjaxr/tests.py
django_pjaxr.egg-info/PKG-INFO
django_pjaxr.egg-info/SOURCES.txt
django_pjaxr.egg-info/dependency_links.txt
django_pjaxr.egg-info/top_level.txt
django_pjaxr/runtests/__init__.py
django_pjaxr/runtests/runtests.py
django_pjaxr/templates/django_pjaxr/pjaxr.html
django_pjaxr/templates/tests/base.html
django_pjaxr/templates/tests/no_pjaxr_page.html
django_pjaxr/templates/tests/page_1.html
django_pjaxr/templates/tests/page_1_content_1.html
django_pjaxr/templates/tests/page_1_content_1_inner_content_1.html
django_pjaxr/templates/tests/page_1_content_1_inner_content_2.html
django_pjaxr/templates/tests/page_1_content_2.html
django_pjaxr/templates/tests/page_2.html
django_pjaxr/templatetags/__init__.py
django_pjaxr/templatetags/pjaxr_extends.py