Metadata-Version: 1.1
Name: django-pjaxr
Version: 1.1.1
Summary: Django extension to use jquery-pjaxr easily!
Home-page: http://noxic-action.de
Author: Jonas Braun
Author-email: jbraun@uni-koblenz.de
License: MIT
Platform: UNKNOWN
Classifier: Development Status :: 4 - Beta
Classifier: Environment :: Web Environment
Classifier: Framework :: Django
Classifier: Intended Audience :: Developers
Classifier: Operating System :: OS Independent
Classifier: Programming Language :: Python
Classifier: Programming Language :: Python :: 3
Classifier: Topic :: Internet :: WWW/HTTP
